image-processing/__init__.py
image-processing/processing/__init__.py
image-processing/processing/combinations.py
image-processing/processing/transformations.py
image-processing/utils/__init__.py
image-processing/utils/io.py
image-processing/utils/plot.py
image_processing/__init__.py
image_processing/processing/__init__.py
image_processing/processing/combinations.py
image_processing/processing/transformations.py
image_processing/utils/__init__.py
image_processing/utils/io.py
image_processing/utils/plot.py
image_processing_furai-0.0.3.dist-info/METADATA
image_processing_furai-0.0.3.dist-info/WHEEL
image_processing_furai-0.0.3.dist-info/top_level.txt
image_processing_furai-0.0.3.dist-info/RECORD
