Metadata-Version: 2.1
Name: image-processing-furai
Version: 0.0.3
Summary: Image processing package to resize and analize images and histogram
Home-page: https://github.com/Furaime/image_processing
Author: Furaime
Author-email: louan.carvalho@gmail.com
License: UNKNOWN
Platform: UNKNOWN
Requires-Python: >=3.8
Requires-Dist: numpy (>=1.20)
Requires-Dist: scikit-image
Requires-Dist: matplotlib
